AUTHORS.rst
LICENSE
MANIFEST.in
README.rst
requirements.txt
requirements_git.txt
requirements_test.txt
setup.py
bin/blohg
blohg/__init__.py
blohg/ext.py
blohg/file_like.py
blohg/models.py
blohg/script.py
blohg/signals.py
blohg/static.py
blohg/templating.py
blohg/utils.py
blohg/vcs.py
blohg/version.py
blohg/views.py
blohg.egg-info/PKG-INFO
blohg.egg-info/SOURCES.txt
blohg.egg-info/dependency_links.txt
blohg.egg-info/not-zip-safe
blohg.egg-info/requires.txt
blohg.egg-info/top_level.txt
blohg/repo_template/config.yaml
blohg/repo_template/content/about.rst
blohg/repo_template/content/attachments/mercurial.png
blohg/repo_template/content/post/example-post.rst
blohg/repo_template/content/post/lorem-ipsum.rst
blohg/repo_template/static/screen.css
blohg/repo_template/templates/base.html
blohg/repo_template/templates/post_list.html
blohg/repo_template/templates/posts.html
blohg/rst_parser/__init__.py
blohg/rst_parser/directives.py
blohg/rst_parser/nodes.py
blohg/rst_parser/roles.py
blohg/rst_parser/writer.py
blohg/templates/404.html
blohg/templates/_posts.html
blohg/templates/robots.txt
blohg/tests/__init__.py
blohg/tests/app.py
blohg/tests/ext.py
blohg/tests/models.py
blohg/tests/templating.py
blohg/tests/utils.py
blohg/tests/vcs.py
blohg/tests/views.py
blohg/tests/rst_parser/__init__.py
blohg/tests/rst_parser/directives.py
blohg/tests/vcs_backends/__init__.py
blohg/tests/vcs_backends/git/__init__.py
blohg/tests/vcs_backends/git/changectx.py
blohg/tests/vcs_backends/git/filectx.py
blohg/tests/vcs_backends/git/utils.py
blohg/tests/vcs_backends/hg/__init__.py
blohg/tests/vcs_backends/hg/changectx.py
blohg/tests/vcs_backends/hg/filectx.py
blohg/vcs_backends/__init__.py
blohg/vcs_backends/git/__init__.py
blohg/vcs_backends/git/changectx.py
blohg/vcs_backends/git/filectx.py
blohg/vcs_backends/hg/__init__.py
blohg/vcs_backends/hg/changectx.py
blohg/vcs_backends/hg/filectx.py
docs/Makefile
docs/about.rst
docs/conf.py
docs/deploy.rst
docs/extend.rst
docs/index.rst
docs/install.rst
docs/license.rst
docs/new-blog.rst
docs/upgrade.rst
docs/write.rst
docs/_build/.keep
docs/_static/.keep
docs/_templates/.keep
share/blohg.wsgi