Metadata-Version: 1.1
Name: blohg
Version: 0.13
Summary: A Mercurial (or Git) based blogging engine
Home-page: http://blohg.org/
Author: Rafael Goncalves Martins
Author-email: rafael@rafaelmartins.eng.br
License: GPL-2
Platform: any
Classifier: Development Status :: 3 - Alpha
Classifier: Environment :: Web Environment
Classifier: License :: OSI Approved :: GNU General Public License (GPL)
Classifier: Operating System :: OS Independent
Classifier: Programming Language :: Python :: 2
Classifier: Topic :: Internet :: WWW/HTTP :: Dynamic Content :: News/Diary
Classifier: Topic :: Internet :: WWW/HTTP :: WSGI :: Application
Classifier: Topic :: Software Development :: Version Control
